LICENSE
LICENSE.txt
MANIFEST.in
README.md
requirements.txt
setup.cfg
setup.py
test_requirements.txt
tests/test_challenge.py
tests/test_client.py
tests/test_hoba.py
tests/test_http.py
tests/test_pgp.py
tests/test_pgp_backend.py
tests/test_retrieve.py
tests/test_session.py
tests/test_uwsgi.py
usumbufu/auth.py
usumbufu/challenge.py
usumbufu/error.py
usumbufu/version.py
usumbufu.egg-info/PKG-INFO
usumbufu.egg-info/SOURCES.txt
usumbufu.egg-info/dependency_links.txt
usumbufu.egg-info/entry_points.txt
usumbufu.egg-info/requires.txt
usumbufu.egg-info/top_level.txt
usumbufu/adapters/__init__.py
usumbufu/adapters/adapter.py
usumbufu/adapters/uwsgi.py
usumbufu/client/__init__.py
usumbufu/client/base.py
usumbufu/client/bearer.py
usumbufu/client/config.py
usumbufu/client/hoba.py
usumbufu/client/pgp.py
usumbufu/client/util.py
usumbufu/ext/http.py
usumbufu/ext/oauth.py
usumbufu/ext/querystring.py
usumbufu/ext/ssl.py
usumbufu/filter/__init__.py
usumbufu/filter/base.py
usumbufu/filter/base64.py
usumbufu/filter/fetcher.py
usumbufu/filter/hoba.py
usumbufu/filter/noop.py
usumbufu/filter/pgp.py
usumbufu/filter/session.py
usumbufu/filter/sha256.py
usumbufu/filter/util.py
usumbufu/retrieve/__init__.py
usumbufu/retrieve/base.py
usumbufu/retrieve/file.py