Metadata-Version: 2.1
Name: usumbufu
Version: 0.3.9
Summary: Multi HTTP authentication handler
Home-page: https://git.defalsify.net/python-usumbufu
Author: Louis Holbrook
Author-email: dev@holbrook.no
License: GPL3
Keywords: http,authentication,hoba,ssl,uwsgi
Classifier: Programming Language :: Python :: 3
Classifier: Operating System :: OS Independent
Classifier: Development Status :: 3 - Alpha
Classifier: Environment :: No Input/Output (Daemon)
Classifier: Topic :: Software Development :: Libraries
Classifier: Intended Audience :: Developers
Classifier: License :: OSI Approved :: GNU General Public License v3 or later (GPLv3+)
Classifier: Topic :: Internet
Requires-Python: >=3.6
License-File: LICENSE
License-File: LICENSE.txt
